Workbook

Sheet 0_Resumen_y_Unit_Economics
B2: WHEELS EXTERNADO — MODELO FINANCIERO Y UNIT ECONOMICS
B3: Portafolio de Evidencias No. 4 | Curso de Emprendimiento | Universidad Externado de Colombia
B4: Equipo 5: Julián Duarte, Julián Jiménez, Santiago Sandoval, Sebastián Ramos, Tomás Rincón
B6: TARIFA POR VIAJE | D6: TAKE-RATE PLATAFORMA | F6: LTV ESPERADO (5 AÑOS) | H6: RAZÓN LTV / CAC
B7: $8.000 COP | D7: $1.200 COP (15%) | F7: $174.897 COP | H7: 29,15 x (Año 1)
B8: Validada en Campo 2 (WTP) | D8: Margen neto: $1.000 COP | F8: Tasa r = 50% (Aulet) | H8: Supera regla 3X (Aulet 19)
B10: 1. DESGLOSE UNITARIO DE CADA VIAJE (UNIT ECONOMICS POR CUPO)
B11: Concepto / Rubro | C11: Valor por Cupo (COP) | D11: % Tarifa | E11: Justificación y Sustentación con Evidencia
B12: Tarifa Total Pagada por el Pasajero | C12: 8000 | D12: 1 | E12: Disposición a pagar media (WTP) validada en 12 entrevistas de Campo 2 (E1-E12). Ahorra $22k frente a taxi.
B13: Compensación Neta al Conductor | C13: 6800 | D13: 0.85 | E13: Con 3-4 cupos/día amortiza $20.400-$27.200 COP cubriendo parqueadero ($22k) y combustible (E5, E7, E12).
B14: Ingreso Bruto de la Plataforma (Take Rate) | C14: 1200 | D14: 0.15 | E14: Comisión competitiva de intermediación tecnológica (15% frente a 25%-30% cobrado por Uber/InDrive).
B15: Costo Directo Transaccional (Pasarela API + Cloud) | C15: 200 | D15: 0.025 | E15: Costo por micropago digital con Nequi/Wompi API ($150) + cloud elástico por transacción ($50).
B16: Margen Bruto de la Plataforma por Viaje | C16: =C14-C15 | D16: =(C14-C15)/C12 | E16: Margen neto de servicio por cupo completado disponible para cubrir costos fijos y marketing.
B18: 2. SUPUESTOS DE FRECUENCIA Y CÁLCULO DE INGRESOS ANUALES POR USUARIO
B19: Parámetro | C19: Valor Base | D19: Unidad | E19: Sustentación / Justificación Académica
B20: Frecuencia de Uso Semanal | C20: 4 | D20: viajes / semana | E20: 2 días de asistencia presencial a clase (2 viajes de ida + 2 viajes de retorno).
B21: Semanas de Clase al Año | C21: 32 | D21: semanas / año | E21: Calendario académico oficial de la Universidad Externado (16 semanas efectivas por semestre x 2).
B22: Total Viajes Anuales por Estudiante | C22: =C20*C21 | D22: viajes / año | E22: Frecuencia semanal multiplicada por semanas del calendario institucional.
B23: Ingreso Anual Bruto por Usuario (Plataforma) | C23: =C22*C14 | D23: COP / usuario / año | E23: Total viajes al año multiplicado por el Take-Rate de la plataforma ($1.200 COP).
B24: Margen Bruto Anual por Usuario (Plataforma) | C24: =C22*C16 | D24: COP / usuario / año | E24: Total viajes al año multiplicado por el Margen Bruto unitario ($1.000 COP).
B26: 3. PRUEBA DE SOSTENIBILIDAD FINANCIERA: REGLA DE LAS 3X (LTV > 3 x CAC)
B27: Horizonte de Tiempo | C27: CAC Rango | D27: CAC Medio | E27: LTV Esperado (5 Años) | F27: Razón LTV / CAC | G27: ¿Cumple Regla 3X? | H27: Diagnóstico Metodológico (Bill Aulet)
B28: Corto Plazo (Año 1) | C28: $4.000 - $8.000 | D28: 6000 | E28: 174897 | F28: =E28/D28 | G28: CUMPLE HOLGADAMENTE | H28: Adquisición de guerrilla en campus. Excede por 9,7x el mínimo requerido de 3X.
B29: Mediano Plazo (Años 2-3) | C29: $2.500 - $4.500 | D29: 3125 | E29: 174897 | F29: =E29/D29 | G29: ALTAMENTE ESCALABLE | H29: Embajadores por facultad y Bienestar Universitario reducen el CAC a la mitad.
B30: Largo Plazo (Años 4-5) | C30: $1.200 - $2.200 | D30: 1666 | E30: 174897 | F30: =E30/D30 | G30: SOSTENIBLE Y VIRAL | H30: Efecto de red orgánico y voz a voz institucional consolidado.

Sheet 1_Modelo_LTV_3_Escenarios
B2: VALOR DE VIDA DEL CLIENTE (LTV) — MODELACIÓN A 5 AÑOS (AULET, PASO 17)
B3: Comparación Rigurosa en Tres Escenarios (Pesimista, Esperado y Optimista) con Tasa de Descuento r = 50% anual
B5: TABLA DE SUPUESTOS POR ESCENARIO
B6: Parámetro Financiero | C6: Escenario Pesimista | D6: Escenario Esperado | E6: Escenario Optimista | F6: Fuente / Justificación Metodológica
B7: Viajes promedio por semana | C7: 3 | D7: 4 | E7: 6 | F7: Campo 2: usuarios habituales (4-6 viajes) vs ocasionales (2-3 viajes).
B8: Semanas de clase al año | C8: 28 | D8: 32 | E8: 34 | F8: Calendario oficial U. Externado (32 sem). Pesimista descuenta semanas de paro/festivos.
B9: Viajes anuales por usuario | C9: =C7*C8 | D9: =D7*D8 | E9: =E7*E8 | F9: Cálculo de viajes por semana multiplicado por semanas de clase anuales.
B10: Tarifa pagada por pasajero | C10: 8000 | D10: 8000 | E10: 8000 | F10: Tarifa validada en Campo 2 ($8.000 COP).
B11: Take-Rate plataforma por viaje | C11: 1200 | D11: 1200 | E11: 1200 | F11: 15% de comisión sobre la tarifa total pagada por el pasajero.
B12: Ingreso Anual Bruto por Cliente | C12: =C9*C11 | D12: =D9*D11 | E12: =E9*E11 | F12: Viajes anuales multiplicados por Take-Rate de la plataforma.
B13: Margen Bruto de Servicio (%) | C13: 0.75 | D13: 0.833333 | E13: 0.85 | F13: Pesimista asume costos mayores de pasarela; Optimista economías de escala en cloud.
B14: Margen Bruto Anual por Cliente | C14: =C12*C13 | D14: =D12*D13 | E14: =E12*E13 | F14: Beneficio neto anual generado por cliente antes de descontar retención.
B15: Tasa de Retención Anual (ret) | C15: 0.7 | D15: 0.8 | E15: 0.85 | F15: Cohortes cautivas de pregrado (4-5 años de carrera universitaria).
B16: Tasa Costo de Capital (r) | C16: 0.5 | D16: 0.5 | E16: 0.5 | F16: Estándar Aulet para startups en etapa temprana financiadas con capital propio / bootstrapping.
B18: FLUJOS DESCONTADOS AÑO A AÑO (AÑO 1 AL AÑO 5) — ESCENARIO ESPERADO (BASE)
B19: Año de Operación | C19: Tasa Retención Acumulada | D19: Beneficio Anual Bruto | E19: Beneficio Neto Esperado | F19: Factor VAN 1/(1+r)^t | G19: Valor Presente (VP) | H19: Lectura y Estado de Cohorte
B20: Año 1 | C20: 1 | D20: =$D$14 | E20: =C20*D20 | F20: =(1/(1+$D$16))^1 | G20: =E20*F20 | H20: Cohorte 100% activa durante el primer año académico.
B21: Año 2 | C21: =$D$15^1 | D21: =$D$14 | E21: =C21*D21 | F21: =(1/(1+$D$16))^2 | G21: =E21*F21 | H21: 80% de la cohorte continúa en 3.° y 4.° semestre.
B22: Año 3 | C22: =$D$15^2 | D22: =$D$14 | E22: =C22*D22 | F22: =(1/(1+$D$16))^3 | G22: =E22*F22 | H22: 64% acumulado de la cohorte activa en 5.° y 6.° semestre.
B23: Año 4 | C23: =$D$15^3 | D23: =$D$14 | E23: =C23*D23 | F23: =(1/(1+$D$16))^4 | G23: =E23*F23 | H23: 51,2% acumulado en 7.° y 8.° semestre.
B24: Año 5 | C24: =$D$15^4 | D24: =$D$14 | E24: =C24*D24 | F24: =(1/(1+$D$16))^5 | G24: =E24*F24 | H24: 40,96% acumulado en año de grado y judicatura.
B25: LTV TOTAL (AÑOS 1-5) | G25: =SUM(G20:G24) | H25: VALOR DE VIDA DEL CLIENTE BASE (R = 50% ANUAL)
B27: RESUMEN COMPARATIVO DE LTV EN LOS TRES ESCENARIOS
B28: Escenario | C28: Ingreso Anual | D28: Margen Bruto | E28: Retención | F28: Costo Capital (r) | G28: LTV Resultante (5 Años) | H28: CAC Máximo Viable (LTV / 3)
B29: Escenario Pesimista | C29: =C12 | D29: =C13 | E29: =C15 | F29: =C16 | G29: =C14*(1/(1+C16)^1 + C15/(1+C16)^2 + C15^2/(1+C16)^3 + C15^3/(1+C16)^4 + C15^4/(1+C16)^5) | H29: =G29/3
B30: Escenario Esperado (Base) | C30: =D12 | D30: =D13 | E30: =D15 | F30: =D16 | G30: =G25 | H30: =G30/3
B31: Escenario Optimista | C31: =E12 | D31: =E13 | E31: =E15 | F31: =E16 | G31: =E14*(1/(1+E16)^1 + E15/(1+E16)^2 + E15^2/(1+E16)^3 + E15^3/(1+E16)^4 + E15^4/(1+E16)^5) | H31: =G31/3
B32: Escenario Esperado con Deuda (r = 12%) | C32: =D12 | D32: =D13 | E32: =D15 | F32: 0.12 | G32: =D14*(1/(1+0.12)^1 + D15/(1+0.12)^2 + D15^2/(1+0.12)^3 + D15^3/(1+0.12)^4 + D15^4/(1+0.12)^5) | H32: =G32/3

Sheet 2_Calculo_CAC_Horizontes
B2: COSTO DE ADQUISICIÓN DE CLIENTES (CAC) — PASO 19 DE BILL AULET
B3: Fórmula: CAC = Gastos de Marketing y Ventas (excl. retención) / Nuevos Clientes Adquiridos
B5: DETALLE DE GASTOS COMERCIALES Y CÁLCULO DEL CAC POR HORIZONTE
B6: Rubro Comercial / Canal de Venta | C6: Corto Plazo (Año 1) | D6: Mediano Plazo (Años 2-3) | E6: Largo Plazo (Años 4-5) | F6: Explicación de la Estrategia Comercial
B7: Material POP, Volantes y Stickers QR en Campus | C7: 600000 | D7: 300000 | E7: 200000 | F7: Piezas gráficas físicas en plazoletas, torniquetes y cafeterías del Externado.
B8: Tiempo Comercial de los 5 Fundadores (Venta Directa) | C8: 1200000 | D8: 400000 | E8: 0 | F8: Horas dedicadas a activación de estudiantes en campus y migración guiada de chats WhatsApp.
B9: Programa de Embajadores por Facultad | C9: 0 | D9: 1200000 | E9: 600000 | F9: Estudiantes líderes remunerados en Derecho, Finanzas, etc., para activar salones.
B10: Presencia en Inducciones de Bienestar Universitario | C10: 0 | D10: 600000 | E10: 200000 | F10: Materiales oficiales en jornadas de inducción de primer semestre.
B11: Programa Digital de Referidos e Incentivos | C11: 0 | D11: 0 | E11: 1000000 | F11: Bonificaciones en viajes ("Invita a un compañero y ambos obtienen descuento").
B12: TOTAL GASTOS DE MARKETING Y VENTAS (COP) | C12: =SUM(C7:C11) | D12: =SUM(D7:D11) | E12: =SUM(E7:E11) | F12: Suma total de inversiones comerciales del período.
B14: NUEVOS CLIENTES ACTIVOS ADQUIRIDOS | C14: 300 | D14: 800 | E14: 1200 | F14: Alumnos convertidos en usuarios recurrentes de la plataforma en el período.
B15: CAC MEDIO CALCULADO (COP / CLIENTE) | C15: =C12/C14 | D15: =D12/D14 | E15: =E12/E14 | F15: Costo medio de adquisición por estudiante. Notar la tendencia descendente (escalabilidad).
B16: CAC Expresado como Rango (Aulet, Paso 19) | C16: $4.000 - $8.000 COP | D16: $2.500 - $4.500 COP | E16: $1.200 - $2.200 COP | F16: Aulet exige presentar el CAC como rango para reflejar incertidumbre comercial.

Sheet 3_Regla_3X_LTV_vs_CAC
B2: COMPARACIÓN LTV vs CAC — VERIFICACIÓN DE LA REGLA DE LAS 3X
B3: Criterio de Sostenibilidad de Bill Aulet: LTV debe ser al menos 3 veces el CAC (LTV > 3 x CAC)
B5: Horizonte Temporal | C5: CAC Medio | D5: LTV Esperado Base | E5: Razón LTV / CAC | F5: Umbral Mínimo Aulet | G5: Evaluación | H5: Conclusión y Acción Estratégica
B6: Corto Plazo (Año 1) | C6: ='2_Calculo_CAC_Horizontes'!C15 | D6: ='1_Modelo_LTV_3_Escenarios'!G25 | E6: =D6/C6 | F6: 3,00 x | G6: SUPERADO (29,15x) | H6: Margen extraordinario desde el inicio debido a la comunidad cautiva.
B7: Mediano Plazo (Años 2-3) | C7: ='2_Calculo_CAC_Horizontes'!D15 | D7: ='1_Modelo_LTV_3_Escenarios'!G25 | E7: =D7/C7 | F7: 3,00 x | G7: SUPERADO (55,97x) | H7: Economías de escala y apoyo de Bienestar Universitario.
B8: Largo Plazo (Años 4-5) | C8: ='2_Calculo_CAC_Horizontes'!E15 | D8: ='1_Modelo_LTV_3_Escenarios'!G25 | E8: =D8/C8 | F8: 3,00 x | G8: SUPERADO (104,98x) | H8: Efecto de red consolida adopción casi a costo marginal cero.
B10: PRUEBA DE ESTRÉS: PEOR ESCENARIO PESIMISTA
B11: LTV Pesimista ($92.408 COP) vs CAC Más Alto ($8.000 COP) | C11: 8000 | D11: ='1_Modelo_LTV_3_Escenarios'!G29 | E11: =D11/C11 | F11: 3,00 x | G11: CUMPLE (11,55x) | H11: Incluso bajo el escenario más adverso de retención y viajes, el modelo supera casi por 4x el umbral.
B13: CONCLUSIÓN FINANCIERA FORMAL DEL ÍTEM 9.1 (AULET, PASO 19)
B14: La razón LTV / CAC de Wheels Externado en el escenario esperado alcanza 29,15x en el corto plazo y supera los 100x en el largo plazo, cumpliendo de manera extraordinaria con la regla de las 3X fijada por Bill Aulet (LTV > 3 x CAC). Incluso bajo el escenario pesimista más riguroso (LTV de $92.408 COP) frente al CAC más elevado ($8.000 COP), la razón se mantiene en 11,55x, casi cuatro veces por encima del umbral mínimo de viabilidad. Este excepcional rendimiento unitario se fundamenta en que el negocio opera sobre un mercado resegmentado de comunidad cerrada: no incurre en costosos presupuestos de pauta digital abierta, sino que capitaliza la densidad geográfica del campus, las redes de confianza preexistentes y la alta recurrencia de los universitarios.

Sheet Plantilla_LTV_Oficial_Aulet
A1: Supuestos | B1: Entradas | D1: Notas
A2: Venta por única vez
A3: Venta inicial promedio | B3: 0 | D3: Este modelo supone que la compra inicial se realiza al comienzo del año 0. (En Wheels es cobro por uso = $0).
A4: Margen bruto - Venta inicial | B4: 0 | D4: Si no hay compra inicial, introduzca 0 $ para el valor medio de la venta inicial.
A5: Tasa de compra del siguiente producto | B5: 0
A6: Año de compra del próximo producto | B6: 0
A8: Compras periódicas | D8: El cliente compra una o más veces al año (128 viajes x $1.200 Take-rate).
A9: Ingresos anuales | B9: ='0_Resumen_y_Unit_Economics'!C23 | D9: Ingreso anual bruto de la plataforma por usuario activo (128 viajes x $1.200 COP).
A10: Margen bruto - Ingresos anuales | B10: ='0_Resumen_y_Unit_Economics'!D16 | D10: Margen bruto de servicio ($1.000 netos / $1.200 brutos = 83,33%).
A11: Tasa de retención | B11: 0.8 | D11: Retención interanual estimada de cohortes universitarias en el Externado.
A13: Ingresos recurrentes
A14: Ingresos recurrentes promedio | B14: 0
A15: Margen bruto - Ingresos recurrentes | B15: 0
A16: # meses de recurrencia en el Año 1 | B16: 0
A17: meses de recurrencia en los años 2-5 | B17: 0
A18: Tasa de retención | B18: 0
A20: Ventas adicionales
A21: Ventas anuales de complementos - Inicio del año 1 | B21: 0
A22: Margen bruto - Ventas adicionales | B22: 0
A23: Tasa de retención | B23: 0
A25: Costo de capital
A26: Costo de capital | B26: 0.5 | D26: Supongamos un 50% si se financia con capital propio / bootstrapping (Estándar Aulet).
A28: Cálculo del LTV | B28: Día | C28: Año | D28: Año | E28: Año | F28: Año | G28: Año
B29: 0 | C29: 1 | D29: 2 | E29: 3 | F29: 4 | G29: 5
A35: Compras periódicas - Ingresos anuales | B35: 0 | C35: =$B$9 | D35: =$B$9 | E35: =$B$9 | F35: =$B$9 | G35: =$B$9
A36: Tasa de retención | C36: =$B$11 | D36: =C36 | E36: =D36 | F36: =E36 | G36: =F36
A37: Tasa de retención acumulada | C37: =C36 | D37: =C37*D36 | E37: =D37*E36 | F37: =E37*F36 | G37: =F37*G36
A38: Margen bruto para ingresos anuales | C38: =$B$10 | D38: =$B$10 | E38: =$B$10 | F38: =$B$10 | G38: =$B$10
A39: Beneficios derivados de los ingresos anuales | B39: 0 | C39: =C35*C37*C38 | D39: =D35*D37*D38 | E39: =E35*E37*E38 | F39: =F35*F37*F38 | G39: =G35*G37*G38
A53: Beneficios totales | B53: =B39 | C53: =C39 | D53: =D39 | E53: =E39 | F53: =F39 | G53: =G39
A55: Tasa de costo de capital | B55: =$B$26 | C55: =$B$26 | D55: =$B$26 | E55: =$B$26 | F55: =$B$26 | G55: =$B$26
A56: Factor de valor actual neto | B56: =(1/(1+$B$26))^B29 | C56: =(1/(1+$B$26))^C29 | D56: =(1/(1+$B$26))^D29 | E56: =(1/(1+$B$26))^E29 | F56: =(1/(1+$B$26))^F29 | G56: =(1/(1+$B$26))^G29
A57: Valor actual de las ganancias | B57: =B53*B56 | C57: =C53*C56 | D57: =D53*D56 | E57: =E53*E56 | F57: =F53*F56 | G57: =G53*G56
A58: LTV / Valor Actual Neto de las Ganancias | B58: =SUM(B57:G57)
A61: Relación LTV/CAC | B61: 3 | C61: 4 | D61: 5 | E61: 6 | F61: 8
A62: CAC Máximo Viable Permitido | B62: =$B$58/B61 | C62: =$B$58/C61 | D62: =$B$58/D61 | E62: =$B$58/E61 | F62: =$B$58/F61 | G62: =$B$58/G61
